MANIFEST.in
README.md
setup.cfg
setup.py
sakshat/__init__.py
sakshat/sakspins.py
sakshat.egg-info/PKG-INFO
sakshat.egg-info/SOURCES.txt
sakshat.egg-info/dependency_links.txt
sakshat.egg-info/requires.txt
sakshat.egg-info/top_level.txt
sakshat/entities/__init__.py
sakshat/entities/buzzer.py
sakshat/entities/digital_display.py
sakshat/entities/digital_display_tm1637.py
sakshat/entities/dip_switch_2bit.py
sakshat/entities/ds18b20.py
sakshat/entities/ic_74hc595.py
sakshat/entities/ic_tm1637.py
sakshat/entities/led.py
sakshat/entities/led_74hc595.py
sakshat/entities/tact.py