Metadata-Version: 1.1
Name: sakshat
Version: 0.0.2
Summary: A fully packaged SAKS SDK
Home-page: https://github.com/spoonysonny/SAKS-SDK
Author: Spoony
Author-email: me@wangxianyuan.com
License: GPL v2.0
Download-URL: https://github.com/spoonysonny/SAKS-SDK/tarball/master
Keywords: sdk,raspi,raspberry pi,saks
Platform: UNKNOWN
Classifier: Development Status :: 5 - Production/Stable
Classifier: Topic :: System :: Hardware :: Hardware Drivers
